upgrade_marshmallow/__init__.py
upgrade_marshmallow/astpp.py
upgrade_marshmallow/cli.py
upgrade_marshmallow/peek.py
upgrade_marshmallow/testing.py
upgrade_marshmallow/upgrade.py
upgrade_marshmallow/utils.py
upgrade_marshmallow-0.1.4.dist-info/LICENSE
upgrade_marshmallow-0.1.4.dist-info/METADATA
upgrade_marshmallow-0.1.4.dist-info/WHEEL
upgrade_marshmallow-0.1.4.dist-info/entry_points.txt
upgrade_marshmallow-0.1.4.dist-info/top_level.txt
upgrade_marshmallow-0.1.4.dist-info/RECORD
